memcrab/__init__.py
memcrab/blocking/__init__.py
memcrab/blocking/connections.py
memcrab/blocking/raw_client.py
memcrab/parsing/__init__.py
memcrab/parsing/aliases.py
memcrab/parsing/parser.py
memcrab/parsing/request.py
memcrab/parsing/response.py
memcrab/parsing/utils.py
memcrab-0.0.1.dist-info/LICENSE
memcrab-0.0.1.dist-info/METADATA
memcrab-0.0.1.dist-info/WHEEL
memcrab-0.0.1.dist-info/RECORD
