Metadata-Version: 2.1
Name: memcrab
Version: 0.0.1
Summary: Memcrab Python Client
License: Apache-2.0
Author: cospectrum
Author-email: severinalexeyv@gmail.com
Requires-Python: >=3.10,<4.0
Classifier: License :: OSI Approved :: Apache Software License
Classifier: Programming Language :: Python :: 3
Classifier: Programming Language :: Python :: 3.10
Classifier: Programming Language :: Python :: 3.11
